echoss_image_utils/__init__.py
echoss_image_utils/echoss_logger.py
echoss_image_utils/img_dataset_split.py
echoss_image_utils/labelme2yolo.py
echoss_image_utils/labelme2yolo_polygon.py
echoss_image_utils-0.1.2.dist-info/METADATA
echoss_image_utils-0.1.2.dist-info/WHEEL
echoss_image_utils-0.1.2.dist-info/top_level.txt
echoss_image_utils-0.1.2.dist-info/RECORD
