Metadata-Version: 2.1
Name: echoss-image-utils
Version: 0.1.2
Summary: echoss AI Bigdata Solution - image utils[image dataset split, labelme2yolo format]
Home-page: 
Author: incheolshin
Author-email: incheolshin@12cm.co.kr
Keywords: echoss,echoss_image_utils,labelme2yolo,labelme,yolo
Requires-Python: >3.7
Requires-Dist: scikit-learn (==1.0.2)
Requires-Dist: labelme (==5.2.1)
Requires-Dist: echoss-s3handler
